{
  "note": "Pending Content Register — every item of unknown information awaiting host confirmation. Nothing here may be invented.",
  "items": [
    {
      "id": "alarm",
      "area": {
        "en": "House",
        "nl": "Huis",
        "fr": "Maison",
        "de": "Haus"
      },
      "item": {
        "en": "Alarm system procedure",
        "nl": "Alarmprocedure",
        "fr": "Procédure d'alarme",
        "de": "Alarmanlagen-Ablauf"
      },
      "status": {
        "en": "Awaiting host workshop",
        "nl": "In afwachting van host-workshop",
        "fr": "En attente de l'atelier hôte",
        "de": "Wartet auf Gastgeber-Workshop"
      },
      "expected": {
        "en": "Before your stay",
        "nl": "Vóór je verblijf",
        "fr": "Avant votre séjour",
        "de": "Vor Ihrem Aufenthalt"
      }
    },
    {
      "id": "locks",
      "area": {
        "en": "Arrival",
        "nl": "Aankomst",
        "fr": "Arrivée",
        "de": "Ankunft"
      },
      "item": {
        "en": "Lock & key procedure",
        "nl": "Slot- & sleutelprocedure",
        "fr": "Procédure serrures & clés",
        "de": "Schloss- & Schlüsselablauf"
      },
      "status": {
        "en": "Awaiting host workshop",
        "nl": "In afwachting van host-workshop",
        "fr": "En attente de l'atelier hôte",
        "de": "Wartet auf Gastgeber-Workshop"
      },
      "expected": {
        "en": "Before your stay",
        "nl": "Vóór je verblijf",
        "fr": "Avant votre séjour",
        "de": "Vor Ihrem Aufenthalt"
      }
    },
    {
      "id": "cat-names",
      "area": {
        "en": "Cats",
        "nl": "Katten",
        "fr": "Chats",
        "de": "Katzen"
      },
      "item": {
        "en": "Cat names & profiles",
        "nl": "Kattennamen & profielen",
        "fr": "Noms & profils des chats",
        "de": "Katzennamen & Profile"
      },
      "status": {
        "en": "Awaiting host workshop",
        "nl": "In afwachting van host-workshop",
        "fr": "En attente de l'atelier hôte",
        "de": "Wartet auf Gastgeber-Workshop"
      },
      "expected": {
        "en": "Before your stay",
        "nl": "Vóór je verblijf",
        "fr": "Avant votre séjour",
        "de": "Vor Ihrem Aufenthalt"
      }
    },
    {
      "id": "feeding",
      "area": {
        "en": "Cats",
        "nl": "Katten",
        "fr": "Chats",
        "de": "Katzen"
      },
      "item": {
        "en": "Feeding instructions",
        "nl": "Voederinstructies",
        "fr": "Consignes de nourrissage",
        "de": "Fütterungshinweise"
      },
      "status": {
        "en": "Awaiting host workshop",
        "nl": "In afwachting van host-workshop",
        "fr": "En attente de l'atelier hôte",
        "de": "Wartet auf Gastgeber-Workshop"
      },
      "expected": {
        "en": "Before your stay",
        "nl": "Vóór je verblijf",
        "fr": "Avant votre séjour",
        "de": "Vor Ihrem Aufenthalt"
      }
    },
    {
      "id": "fireplace",
      "area": {
        "en": "House",
        "nl": "Huis",
        "fr": "Maison",
        "de": "Haus"
      },
      "item": {
        "en": "Fireplace guide",
        "nl": "Haardgids",
        "fr": "Guide cheminée",
        "de": "Kaminanleitung"
      },
      "status": {
        "en": "Awaiting host workshop",
        "nl": "In afwachting van host-workshop",
        "fr": "En attente de l'atelier hôte",
        "de": "Wartet auf Gastgeber-Workshop"
      },
      "expected": {
        "en": "Before your stay",
        "nl": "Vóór je verblijf",
        "fr": "Avant votre séjour",
        "de": "Vor Ihrem Aufenthalt"
      }
    },
    {
      "id": "hot-tub",
      "area": {
        "en": "Garden",
        "nl": "Tuin",
        "fr": "Jardin",
        "de": "Garten"
      },
      "item": {
        "en": "Hot tub guide",
        "nl": "Hottub-gids",
        "fr": "Guide jacuzzi",
        "de": "Whirlpool-Anleitung"
      },
      "status": {
        "en": "Awaiting host workshop",
        "nl": "In afwachting van host-workshop",
        "fr": "En attente de l'atelier hôte",
        "de": "Wartet auf Gastgeber-Workshop"
      },
      "expected": {
        "en": "Before your stay",
        "nl": "Vóór je verblijf",
        "fr": "Avant votre séjour",
        "de": "Vor Ihrem Aufenthalt"
      }
    },
    {
      "id": "bbq",
      "area": {
        "en": "Garden",
        "nl": "Tuin",
        "fr": "Jardin",
        "de": "Garten"
      },
      "item": {
        "en": "BBQ guide",
        "nl": "BBQ-gids",
        "fr": "Guide barbecue",
        "de": "Grill-Anleitung"
      },
      "status": {
        "en": "Awaiting host workshop",
        "nl": "In afwachting van host-workshop",
        "fr": "En attente de l'atelier hôte",
        "de": "Wartet auf Gastgeber-Workshop"
      },
      "expected": {
        "en": "Before your stay",
        "nl": "Vóór je verblijf",
        "fr": "Avant votre séjour",
        "de": "Vor Ihrem Aufenthalt"
      }
    },
    {
      "id": "appliances",
      "area": {
        "en": "House",
        "nl": "Huis",
        "fr": "Maison",
        "de": "Haus"
      },
      "item": {
        "en": "Appliance models & instructions",
        "nl": "Toestelmodellen & instructies",
        "fr": "Modèles & instructions des appareils",
        "de": "Gerätemodelle & Anleitungen"
      },
      "status": {
        "en": "Awaiting host workshop",
        "nl": "In afwachting van host-workshop",
        "fr": "En attente de l'atelier hôte",
        "de": "Wartet auf Gastgeber-Workshop"
      },
      "expected": {
        "en": "Before your stay",
        "nl": "Vóór je verblijf",
        "fr": "Avant votre séjour",
        "de": "Vor Ihrem Aufenthalt"
      }
    },
    {
      "id": "emergency-contacts",
      "area": {
        "en": "Help",
        "nl": "Hulp",
        "fr": "Aide",
        "de": "Hilfe"
      },
      "item": {
        "en": "Local emergency contacts (nearest hospital, vet)",
        "nl": "Lokale noodcontacten (dichtstbijzijnd ziekenhuis, dierenarts)",
        "fr": "Contacts d'urgence locaux (hôpital le plus proche, vétérinaire)",
        "de": "Lokale Notfallkontakte (nächstes Krankenhaus, Tierarzt)"
      },
      "status": {
        "en": "Awaiting host workshop",
        "nl": "In afwachting van host-workshop",
        "fr": "En attente de l'atelier hôte",
        "de": "Wartet auf Gastgeber-Workshop"
      },
      "expected": {
        "en": "Before your stay",
        "nl": "Vóór je verblijf",
        "fr": "Avant votre séjour",
        "de": "Vor Ihrem Aufenthalt"
      }
    },
    {
      "id": "house-rules",
      "area": {
        "en": "House",
        "nl": "Huis",
        "fr": "Maison",
        "de": "Haus"
      },
      "item": {
        "en": "Full house rules",
        "nl": "Volledige huisregels",
        "fr": "Règles complètes de la maison",
        "de": "Vollständige Hausregeln"
      },
      "status": {
        "en": "Awaiting host workshop",
        "nl": "In afwachting van host-workshop",
        "fr": "En attente de l'atelier hôte",
        "de": "Wartet auf Gastgeber-Workshop"
      },
      "expected": {
        "en": "Before your stay",
        "nl": "Vóór je verblijf",
        "fr": "Avant votre séjour",
        "de": "Vor Ihrem Aufenthalt"
      }
    },
    {
      "id": "local-recs",
      "area": {
        "en": "Guide",
        "nl": "Gids",
        "fr": "Guide",
        "de": "Guide"
      },
      "item": {
        "en": "Host's local recommendations",
        "nl": "Lokale tips van de gastheer",
        "fr": "Recommandations locales de l'hôte",
        "de": "Lokale Tipps des Gastgebers"
      },
      "status": {
        "en": "Awaiting host workshop",
        "nl": "In afwachting van host-workshop",
        "fr": "En attente de l'atelier hôte",
        "de": "Wartet auf Gastgeber-Workshop"
      },
      "expected": {
        "en": "Before your stay",
        "nl": "Vóór je verblijf",
        "fr": "Avant votre séjour",
        "de": "Vor Ihrem Aufenthalt"
      }
    },
    {
      "id": "checkout-process",
      "area": {
        "en": "Checkout",
        "nl": "Uitchecken",
        "fr": "Départ",
        "de": "Check-out"
      },
      "item": {
        "en": "Checkout process & times",
        "nl": "Uitcheckproces & tijden",
        "fr": "Processus & horaires de départ",
        "de": "Check-out-Ablauf & Zeiten"
      },
      "status": {
        "en": "Awaiting host workshop",
        "nl": "In afwachting van host-workshop",
        "fr": "En attente de l'atelier hôte",
        "de": "Wartet auf Gastgeber-Workshop"
      },
      "expected": {
        "en": "Before your stay",
        "nl": "Vóór je verblijf",
        "fr": "Avant votre séjour",
        "de": "Vor Ihrem Aufenthalt"
      }
    },
    {
      "id": "waste",
      "area": {
        "en": "Checkout",
        "nl": "Uitchecken",
        "fr": "Départ",
        "de": "Check-out"
      },
      "item": {
        "en": "Waste sorting rules",
        "nl": "Afvalsorteerregels",
        "fr": "Règles de tri des déchets",
        "de": "Mülltrennungsregeln"
      },
      "status": {
        "en": "Awaiting host workshop",
        "nl": "In afwachting van host-workshop",
        "fr": "En attente de l'atelier hôte",
        "de": "Wartet auf Gastgeber-Workshop"
      },
      "expected": {
        "en": "Before your stay",
        "nl": "Vóór je verblijf",
        "fr": "Avant votre séjour",
        "de": "Vor Ihrem Aufenthalt"
      }
    },
    {
      "id": "quiet-hours",
      "area": {
        "en": "House",
        "nl": "Huis",
        "fr": "Maison",
        "de": "Haus"
      },
      "item": {
        "en": "Quiet hours & noise policy",
        "nl": "Stiltemomenten & geluidsafspraken",
        "fr": "Heures de calme & consignes de bruit",
        "de": "Ruhezeiten & Lärmregeln"
      },
      "status": {
        "en": "Awaiting host workshop",
        "nl": "In afwachting van host-workshop",
        "fr": "En attente de l'atelier hôte",
        "de": "Wartet auf Gastgeber-Workshop"
      },
      "expected": {
        "en": "Before your stay",
        "nl": "Vóór je verblijf",
        "fr": "Avant votre séjour",
        "de": "Vor Ihrem Aufenthalt"
      }
    },
    {
      "id": "hot-tub-safety",
      "area": {
        "en": "Garden",
        "nl": "Tuin",
        "fr": "Jardin",
        "de": "Garten"
      },
      "item": {
        "en": "Hot tub — children & safety rules",
        "nl": "Hottub — kinderen & veiligheidsregels",
        "fr": "Jacuzzi — enfants & règles de sécurité",
        "de": "Whirlpool — Kinder & Sicherheitsregeln"
      },
      "status": {
        "en": "Awaiting host workshop",
        "nl": "In afwachting van host-workshop",
        "fr": "En attente de l'atelier hôte",
        "de": "Wartet auf Gastgeber-Workshop"
      },
      "expected": {
        "en": "Before your stay",
        "nl": "Vóór je verblijf",
        "fr": "Avant votre séjour",
        "de": "Vor Ihrem Aufenthalt"
      }
    },
    {
      "id": "first-aid",
      "area": {
        "en": "Help",
        "nl": "Hulp",
        "fr": "Aide",
        "de": "Hilfe"
      },
      "item": {
        "en": "First aid kit & defibrillator location",
        "nl": "EHBO-kit & locatie defibrillator",
        "fr": "Trousse de secours & emplacement du défibrillateur",
        "de": "Erste-Hilfe-Set & Defibrillator-Standort"
      },
      "status": {
        "en": "Awaiting host workshop",
        "nl": "In afwachting van host-workshop",
        "fr": "En attente de l'atelier hôte",
        "de": "Wartet auf Gastgeber-Workshop"
      },
      "expected": {
        "en": "Before your stay",
        "nl": "Vóór je verblijf",
        "fr": "Avant votre séjour",
        "de": "Vor Ihrem Aufenthalt"
      }
    },
    {
      "id": "outage",
      "area": {
        "en": "Help",
        "nl": "Hulp",
        "fr": "Aide",
        "de": "Hilfe"
      },
      "item": {
        "en": "Power & water outage steps",
        "nl": "Stappen bij stroom- of waterpanne",
        "fr": "Que faire en cas de coupure d'eau ou d'électricité",
        "de": "Schritte bei Strom- oder Wasserausfall"
      },
      "status": {
        "en": "Awaiting host workshop",
        "nl": "In afwachting van host-workshop",
        "fr": "En attente de l'atelier hôte",
        "de": "Wartet auf Gastgeber-Workshop"
      },
      "expected": {
        "en": "Before your stay",
        "nl": "Vóór je verblijf",
        "fr": "Avant votre séjour",
        "de": "Vor Ihrem Aufenthalt"
      }
    }
  ]
}